dowse/__init__.py
dowse/dsl/__init__.py
dowse/dsl/_types.py
dowse/dsl/example.py
dowse/dsl/exceptions.py
dowse/dsl/executors/__init__.py
dowse/dsl/executors/base.py
dowse/dsl/operators/__init__.py
dowse/dsl/operators/base.py
dowse/dsl/operators/special.py
dowse/dsl/operators/stack_op.py
dowse/dsl/stack.py
dowse/dsl/syntax.py
dowse/dsl/types.py
dowse/exceptions.py
dowse/impls/__init__.py
dowse/impls/basic/__init__.py
dowse/impls/basic/context.py
dowse/impls/basic/effects/__init__.py
dowse/impls/basic/effects/printer.py
dowse/impls/basic/llms/__init__.py
dowse/impls/basic/llms/classifier/PROMPT.txt
dowse/impls/basic/llms/classifier/__init__.py
dowse/impls/basic/llms/commands/PROMPT.txt
dowse/impls/basic/llms/commands/__init__.py
dowse/impls/basic/llms/commands/examples.py
dowse/impls/basic/llms/preprocessor/PROMPT.txt
dowse/impls/basic/llms/preprocessor/__init__.py
dowse/impls/basic/llms/preprocessor/examples.py
dowse/impls/basic/llms/questions/PROMPT.txt
dowse/impls/basic/llms/questions/__init__.py
dowse/impls/basic/source/__init__.py
dowse/impls/basic/source/twitter/__init__.py
dowse/impls/basic/source/twitter/mock.py
dowse/impls/basic/tools.py
dowse/impls/basic/user.py
dowse/impls/executors/__init__.py
dowse/impls/executors/noop.py
dowse/interfaces/__init__.py
dowse/interfaces/effects.py
dowse/interfaces/executor/__init__.py
dowse/interfaces/executor/agent.py
dowse/interfaces/executor/base.py
dowse/interfaces/executor/chain.py
dowse/interfaces/executor/executor.py
dowse/interfaces/llms/__init__.py
dowse/interfaces/llms/classifier.py
dowse/interfaces/llms/context.py
dowse/interfaces/loaders/__init__.py
dowse/interfaces/loaders/base.py
dowse/interfaces/loaders/examples.py
dowse/interfaces/loaders/prompts.py
dowse/interfaces/loaders/tools.py
dowse/interfaces/processor/__init__.py
dowse/interfaces/processor/agent.py
dowse/interfaces/processor/base.py
dowse/interfaces/processor/preprocess.py
dowse/interfaces/sources/__init__.py
dowse/interfaces/sources/source.py
dowse-0.1.6.post1.dist-info/LICENSE
dowse-0.1.6.post1.dist-info/METADATA
dowse-0.1.6.post1.dist-info/WHEEL
dowse-0.1.6.post1.dist-info/entry_points.txt
dowse-0.1.6.post1.dist-info/RECORD
