Metadata-Version: 2.3
Name: dowse
Version: 0.1.6.post1
Summary: 
Author: johnny-emp
Author-email: johnny@empyrealsdk.com
Requires-Python: >=3.12
Classifier: Programming Language :: Python :: 3
Classifier: Programming Language :: Python :: 3.12
Classifier: Programming Language :: Python :: 3.13
Requires-Dist: emp-agents (>=0.3.0,<0.4.0)
Requires-Dist: eth-rpc-py (>=0.1.26,<0.2.0)
Requires-Dist: eth-typeshed-py (>=0.1.26,<0.2.0)
Requires-Dist: python-dotenv (>=1.0.1,<2.0.0)
